{
    "dataRoles": [
        {
            "displayName": "KPI Value",
            "name": "kpiValue",
            "kind": "Measure",
            "requiredTypes": [
                {
                    "numeric": true
                }
            ]
        },
        {
            "displayName": "Comparison Value",
            "name": "comparisonValue",
            "kind": "Measure",
            "requiredTypes": [
                {
                    "numeric": true
                }
            ]
        },
        {
            "displayName": "KPI Label",
            "name": "kpiLabel",
            "kind": "Grouping"
        }
    ],
    "objects": {
        "kpiCard": {
            "displayName": "KPI Card Settings",
            "properties": {
                "showLabel": {
                    "displayName": "Show Label",
                    "type": {
                        "bool": true
                    }
                },
                "labelText": {
                    "displayName": "Label Text",
                    "type": {
                        "text": true
                    }
                },
                "valueFormat": {
                    "displayName": "Value Format",
                    "type": {
                        "enumeration": [
                            {
                                "displayName": "Number",
                                "value": "number"
                            },
                            {
                                "displayName": "Currency",
                                "value": "currency"
                            },
                            {
                                "displayName": "Percentage",
                                "value": "percentage"
                            }
                        ]
                    }
                },
                "showComparison": {
                    "displayName": "Show Comparison",
                    "type": {
                        "bool": true
                    }
                },
                "comparisonType": {
                    "displayName": "Comparison Type",
                    "type": {
                        "enumeration": [
                            {
                                "displayName": "Difference",
                                "value": "difference"
                            },
                            {
                                "displayName": "Percentage",
                                "value": "percentage"
                            }
                        ]
                    }
                },
                "positiveColor": {
                    "displayName": "Positive Change Color",
                    "type": {
                        "fill": {
                            "solid": {
                                "color": true
                            }
                        }
                    }
                },
                "negativeColor": {
                    "displayName": "Negative Change Color",
                    "type": {
                        "fill": {
                            "solid": {
                                "color": true
                            }
                        }
                    }
                },
                "neutralColor": {
                    "displayName": "Neutral Color",
                    "type": {
                        "fill": {
                            "solid": {
                                "color": true
                            }
                        }
                    }
                },
                "fontFamily": {
                    "displayName": "Font Family",
                    "type": {
                        "formatting": {
                            "fontFamily": true
                        }
                    }
                },
                "fontSize": {
                    "displayName": "Font Size",
                    "type": {
                        "formatting": {
                            "fontSize": true
                        }
                    }
                },
                "backgroundColor": {
                    "displayName": "Background Color",
                    "type": {
                        "fill": {
                            "solid": {
                                "color": true
                            }
                        }
                    }
                }
            }
        }
    },
    "dataViewMappings": [
        {
            "conditions": [
                {
                    "kpiValue": {
                        "max": 1
                    }
                }
            ],
            "categorical": {
                "categories": {
                    "for": {
                        "in": "kpiLabel"
                    },
                    "dataReductionAlgorithm": {
                        "top": {}
                    }
                },
                "values": {
                    "select": [
                        {
                            "bind": {
                                "to": "kpiValue"
                            }
                        },
                        {
                            "bind": {
                                "to": "comparisonValue"
                            }
                        }
                    ]
                }
            }
        }
    ],
    "privileges": []
}
